folio_migration_tools/__init__.py
folio_migration_tools/__main__.py
folio_migration_tools/circulation_helper.py
folio_migration_tools/colors.py
folio_migration_tools/config_file_load.py
folio_migration_tools/custom_dict.py
folio_migration_tools/custom_exceptions.py
folio_migration_tools/extradata_writer.py
folio_migration_tools/folder_structure.py
folio_migration_tools/helper.py
folio_migration_tools/holdings_helper.py
folio_migration_tools/i18n_config.py
folio_migration_tools/library_configuration.py
folio_migration_tools/mapper_base.py
folio_migration_tools/mapping_file_transformation/__init__.py
folio_migration_tools/mapping_file_transformation/courses_mapper.py
folio_migration_tools/mapping_file_transformation/holdings_mapper.py
folio_migration_tools/mapping_file_transformation/item_mapper.py
folio_migration_tools/mapping_file_transformation/manual_fee_fines_mapper.py
folio_migration_tools/mapping_file_transformation/mapping_file_mapper_base.py
folio_migration_tools/mapping_file_transformation/notes_mapper.py
folio_migration_tools/mapping_file_transformation/order_mapper.py
folio_migration_tools/mapping_file_transformation/organization_mapper.py
folio_migration_tools/mapping_file_transformation/ref_data_mapping.py
folio_migration_tools/mapping_file_transformation/user_mapper.py
folio_migration_tools/marc_rules_transformation/__init__.py
folio_migration_tools/marc_rules_transformation/conditions.py
folio_migration_tools/marc_rules_transformation/holdings_statementsparser.py
folio_migration_tools/marc_rules_transformation/hrid_handler.py
folio_migration_tools/marc_rules_transformation/loc_language_codes.xml
folio_migration_tools/marc_rules_transformation/marc_file_processor.py
folio_migration_tools/marc_rules_transformation/marc_reader_wrapper.py
folio_migration_tools/marc_rules_transformation/rules_mapper_authorities.py
folio_migration_tools/marc_rules_transformation/rules_mapper_base.py
folio_migration_tools/marc_rules_transformation/rules_mapper_bibs.py
folio_migration_tools-1.9.10.dist-info/METADATA
folio_migration_tools-1.9.10.dist-info/WHEEL
folio_migration_tools-1.9.10.dist-info/entry_points.txt
folio_migration_tools-1.9.10.dist-info/licenses/LICENSE
folio_migration_tools-1.9.10.dist-info/RECORD
