Metadata-Version: 2.4
Name: folio_migration_tools
Version: 1.9.10
Summary: A tool allowing you to migrate data from legacy ILS:s (Library systems) into FOLIO LSP
License-Expression: MIT
License-File: LICENSE
Keywords: FOLIO,ILS,LSP,Library Systems,MARC21,Library data
Author: Theodor Tolstoy
Author-email: github.teddes@tolstoy.se
Requires-Python: >=3.10,<4.0
Classifier: Programming Language :: Python :: 3
Classifier: Programming Language :: Python :: 3.10
Classifier: Programming Language :: Python :: 3.11
Classifier: Programming Language :: Python :: 3.12
Classifier: Programming Language :: Python :: 3.13
Classifier: Programming Language :: Python :: 3.14
Provides-Extra: docs
Requires-Dist: argparse-prompt (>=0.0.5,<0.0.6)
Requires-Dist: art (>=6.5,<7.0)
Requires-Dist: deepdiff (>=6.2.3,<7.0.0)
Requires-Dist: defusedxml (>=0.7.1,<0.8.0)
Requires-Dist: folio-data-import (>=0.4.1)
Requires-Dist: folio-uuid (>=1.0.0,<2.0.0)
Requires-Dist: folioclient (>=0.70.1,<0.71.0)
Requires-Dist: pyaml (>=21.10.1,<22.0.0)
Requires-Dist: pydantic (>=1.10.2,<2.0.0)
Requires-Dist: pyhumps (>=3.7.3,<4.0.0)
Requires-Dist: pymarc (>=5.2.3,<6.0.0)
Requires-Dist: python-dateutil (>=2.8.2,<3.0.0)
Requires-Dist: python-i18n (>=0.3.9,<0.4.0)
Project-URL: Documentation, https://folio-migration-tools.readthedocs.io/en/latest/
Project-URL: Homepage, https://github.com/folio-fse/folio_migration_tools
Project-URL: Repository, https://github.com/FOLIO-FSE/folio_migration_tools
